Pynomic/__init__.py
Pynomic/core/__init__.py
Pynomic/core/core.py
Pynomic/core/plot.py
Pynomic/io/__init__.py
Pynomic/io/get_plot_bands.py
pynomic-0.0.2.dist-info/licenses/LICENSE
pynomic-0.0.2.dist-info/METADATA
pynomic-0.0.2.dist-info/WHEEL
pynomic-0.0.2.dist-info/top_level.txt
pynomic-0.0.2.dist-info/RECORD
