Metadata-Version: 2.4
Name: Pynomic
Version: 0.0.2
Summary: Python library for data extraction from drone orthomosaics in plant breeding trials
Author-email: "Fiore Juan M." <fiorejuanm@mi.unc.edu.ar>
License: The MIT License
Project-URL: Homepage, https://github.com/JMFiore/Pynomic
Keywords: UAV,RGB,Multispectral,Pipeline
Classifier: Development Status :: 2 - Pre-Alpha
Classifier: Intended Audience :: Education
Classifier: Intended Audience :: Science/Research
Classifier: License :: OSI Approved :: MIT License
Classifier: Operating System :: OS Independent
Classifier: Programming Language :: Python
Classifier: Programming Language :: Python :: 3.8
Classifier: Programming Language :: Python :: 3.9
Classifier: Programming Language :: Python :: 3.10
Classifier: Programming Language :: Python :: 3.11
Classifier: Topic :: Scientific/Engineering
License-File: LICENSE
Requires-Dist: attrs
Requires-Dist: numpy
Requires-Dist: python-dateutil
Requires-Dist: seaborn
Requires-Dist: pandas
Requires-Dist: rasterio
Requires-Dist: matplotlib
Requires-Dist: shapely
Requires-Dist: pillow
Requires-Dist: numcodecs<0.16.0
Requires-Dist: zarr==2.18.2
Requires-Dist: scikit-learn
Requires-Dist: opencv-python
Requires-Dist: pandas-geojson
Requires-Dist: scikit-image
Requires-Dist: geopandas
Requires-Dist: statsmodels
Dynamic: license-file
